Metadata-Version: 2.4
Name: textprettify
Version: 1.0.0
Summary: A comprehensive Python library for text formatting, transformation, and analysis
Home-page: https://github.com/mmssajith/TextPrettify
Author: Sajith
Author-email: Sajith <mmssajith@gmail.com>
License: MIT
Project-URL: Homepage, https://github.com/mmssajith/TextPrettify
Project-URL: Documentation, https://github.com/mmssajith/TextPrettify#readme
Project-URL: Bug Reports, https://github.com/mmssajith/TextPrettify/issues
Project-URL: Source, https://github.com/mmssajith/TextPrettify
Keywords: text,string,formatting,slug,whitespace,utility,analysis,readability,statistics,case-conversion,unicode,normalization,text-analysis
Classifier: Development Status :: 4 - Beta
Classifier: Intended Audience :: Developers
Classifier: Topic :: Software Development :: Libraries :: Python Modules
Classifier: Topic :: Text Processing
Classifier: Topic :: Text Processing :: Linguistic
Classifier: License :: OSI Approved :: MIT License
Classifier: Programming Language :: Python :: 3
Classifier: Programming Language :: Python :: 3.8
Classifier: Programming Language :: Python :: 3.9
Classifier: Programming Language :: Python :: 3.10
Classifier: Programming Language :: Python :: 3.11
Classifier: Programming Language :: Python :: 3.12
Requires-Python: >=3.8
License-File: LICENSE
Provides-Extra: dev
Requires-Dist: pytest>=7.0.0; extra == "dev"
Requires-Dist: pytest-cov>=4.0.0; extra == "dev"
Dynamic: author
Dynamic: home-page
Dynamic: license-file
Dynamic: requires-python
